atomcloud/__init__.py
atomcloud/example_data.py
atomcloud/analysis/__init__.py
atomcloud/analysis/analysis_utils.py
atomcloud/analysis/fit_metrics.py
atomcloud/analysis/image_scales.py
atomcloud/analysis/rescale_params.py
atomcloud/common/__init__.py
atomcloud/common/registry.py
atomcloud/fits/__init__.py
atomcloud/fits/func_fits.py
atomcloud/fits/multi_fit.py
atomcloud/fits/sum_fit.py
atomcloud/functions/__init__.py
atomcloud/functions/func_base.py
atomcloud/functions/funcs_1d.py
atomcloud/functions/funcs_2d.py
atomcloud/functions/funcs_sumfit.py
atomcloud/functions/multi_base.py
atomcloud/functions/multi_funcs.py
atomcloud/functions/jax_funcs/__init__.py
atomcloud/functions/jax_funcs/spence.py
atomcloud/mixed_level/__init__.py
atomcloud/mixed_level/bimodal.py
atomcloud/mixed_level/mixed_base.py
atomcloud/mixed_level/thermal.py
atomcloud/plots/__init__.py
atomcloud/plots/plot_1d.py
atomcloud/plots/plot_2d.py
atomcloud/plots/plot_base.py
atomcloud/plots/plot_sumfit.py
atomcloud/process_fits/__init__.py
atomcloud/process_fits/analyze.py
atomcloud/process_fits/base.py
atomcloud/process_fits/combine.py
atomcloud/process_fits/format.py
atomcloud/process_fits/iterate.py
atomcloud/process_fits/plot.py
atomcloud/process_fits/rescale.py
atomcloud/utils/__init__.py
atomcloud/utils/check_utils.py
atomcloud/utils/fit_utils.py
atomcloud/utils/img_utils.py
atomcloud/utils/mask_utils.py
atomcloud/utils/uncertain_utils.py
atomcloud-0.0.1.dist-info/METADATA
atomcloud-0.0.1.dist-info/WHEEL
atomcloud-0.0.1.dist-info/licenses/LICENSE
atomcloud-0.0.1.dist-info/RECORD
