Metadata-Version: 2.1
Name: atomcloud
Version: 0.0.1
Summary: Conventional method for fitting atom cloud, BECs and bimodal atom cloud/BEC distributions in 1D and 2D.
Project-URL: repository, https://github.com/lucashofer/atomcloud
Author: Lucas Hofer
License:                                  Apache License
License-File: LICENSE
Keywords: BEC,deep-learning,equinox,fitting
Classifier: Development Status :: 3 - Alpha
Classifier: Intended Audience :: Developers
Classifier: Intended Audience :: Science/Research
Classifier: License :: OSI Approved :: Apache Software License
Classifier: Natural Language :: English
Classifier: Programming Language :: Python :: 3
Classifier: Topic :: Scientific/Engineering :: Artificial Intelligence
Classifier: Topic :: Scientific/Engineering :: Physics
Requires-Python: ~=3.9
Requires-Dist: matplotlib
Requires-Dist: numpy
Requires-Dist: pandas
Requires-Dist: scipy
Requires-Dist: tabulate
Requires-Dist: uncertainties
